pyrcv/__init__.py
pyrcv/cli.py
pyrcv/pyrcv.py
pyrcv/transform.py
pyrcv/types.py
pyrcv/viz.py
pyrcv-1.2.1.dist-info/licenses/LICENSE
pyrcv-1.2.1.dist-info/METADATA
pyrcv-1.2.1.dist-info/WHEEL
pyrcv-1.2.1.dist-info/entry_points.txt
pyrcv-1.2.1.dist-info/top_level.txt
pyrcv-1.2.1.dist-info/RECORD
