Metadata-Version: 2.4
Name: pyrcv
Version: 1.2.1
Summary: Python API for adjudicating single transferable vote elections.  Also contains basic web server to adjudicate results in CSV format.
Home-page: https://github.com/chrisroat/pyrcv
Author: Chris Roat
Author-email: chris.roat@gmail.com
License: GNU General Public License v3
Project-URL: Bug Tracker, https://github.com/chrisroat/pyrcv/issues
Project-URL: Production Server, https://www.pyrcv.org
Classifier: Development Status :: 5 - Production/Stable
Classifier: Intended Audience :: Other Audience
Classifier: License :: OSI Approved :: GNU General Public License v3 (GPLv3)
Classifier: Natural Language :: English
Classifier: Programming Language :: Python :: 3.11
Classifier: Programming Language :: Python :: 3.12
Classifier: Programming Language :: Python :: 3.13
Classifier: Operating System :: OS Independent
Requires-Python: >=3.11
License-File: LICENSE
Requires-Dist: click>=8
Requires-Dist: icontract>=2.6
Requires-Dist: numpy>=1.21
Requires-Dist: pandas>=1.5
Requires-Dist: plotly>=5.13
Dynamic: license-file
